tonapi/__init__.py
tonapi/constants.py
tonapi/exceptions.py
tonapi/utils.py
tonapi/async_tonapi/__init__.py
tonapi/async_tonapi/client.py
tonapi/async_tonapi/methods/__init__.py
tonapi/async_tonapi/methods/account.py
tonapi/async_tonapi/methods/auction.py
tonapi/async_tonapi/methods/blockchain.py
tonapi/async_tonapi/methods/dns.py
tonapi/async_tonapi/methods/jetton.py
tonapi/async_tonapi/methods/nft.py
tonapi/async_tonapi/methods/oauth.py
tonapi/async_tonapi/methods/subscription.py
tonapi/async_tonapi/methods/system.py
tonapi/async_tonapi/methods/trace.py
tonapi/tonapi/__init__.py
tonapi/tonapi/client.py
tonapi/tonapi/methods/__init__.py
tonapi/tonapi/methods/account.py
tonapi/tonapi/methods/auction.py
tonapi/tonapi/methods/blockchain.py
tonapi/tonapi/methods/dns.py
tonapi/tonapi/methods/jetton.py
tonapi/tonapi/methods/nft.py
tonapi/tonapi/methods/oauth.py
tonapi/tonapi/methods/subscription.py
tonapi/tonapi/methods/system.py
tonapi/tonapi/methods/trace.py
tonapi/types/__init__.py
tonapi/types/account.py
tonapi/types/auction.py
tonapi/types/blockchain.py
tonapi/types/dns.py
tonapi/types/event.py
tonapi/types/jetton.py
tonapi/types/nft.py
tonapi/types/oauth.py
tonapi/types/subscription.py
tonapi/types/system.py
tonapi/types/trace.py
tonapi.io-0.0.10.dist-info/LICENSE
tonapi.io-0.0.10.dist-info/METADATA
tonapi.io-0.0.10.dist-info/WHEEL
tonapi.io-0.0.10.dist-info/top_level.txt
tonapi.io-0.0.10.dist-info/RECORD
