Metadata-Version: 2.1
Name: tonapi.io
Version: 0.0.10
Summary: TON API. Provide access to indexed TON blockchain.
Home-page: https://github.com/nessshon/tonapi.io/
Author: nessshon
License: UNKNOWN
Platform: UNKNOWN
Classifier: Programming Language :: Python :: 3
Classifier: License :: OSI Approved :: MIT License
Classifier: Operating System :: OS Independent
Requires-Python: >=3.10
License-File: LICENSE
Requires-Dist: aiohttp (>=3.8.3)
Requires-Dist: libscrc (>=1.8.1)
Requires-Dist: pydantic (>=1.10.4)
Requires-Dist: requests (>=2.28.2)
